deepseek_api/__init__.py
deepseek_api/constants.py
deepseek_api/deepseek_api.py
deepseek_api/errors.py
deepseek_api-0.5.3.1.dist-info/LICENSE
deepseek_api-0.5.3.1.dist-info/METADATA
deepseek_api-0.5.3.1.dist-info/WHEEL
deepseek_api-0.5.3.1.dist-info/top_level.txt
deepseek_api-0.5.3.1.dist-info/RECORD
