Metadata-Version: 2.1
Name: deepseek_api
Version: 0.5.3.1
Summary: An unofficial Python API wrapper for chat.Deepseek.com
License-File: LICENSE
Requires-Dist: certifi
Requires-Dist: charset-normalizer
Requires-Dist: idna
Requires-Dist: python-dotenv
Requires-Dist: requests
Requires-Dist: urllib3
Requires-Dist: PyJWT
Requires-Dist: aiofiles
Requires-Dist: aiohttp
